s3arch.py
setup.py
s3arch.egg-info/PKG-INFO
s3arch.egg-info/SOURCES.txt
s3arch.egg-info/dependency_links.txt
s3arch.egg-info/entry_points.txt
s3arch.egg-info/requires.txt
s3arch.egg-info/top_level.txt