Metadata-Version: 1.0
Name: s3arch
Version: 0.1
Summary: Create local backups of S3 buckets
Home-page: https://github.com/jcarbaugh/s3arch/
Author: Jeremy Carbaugh
Author-email: jcarbaugh@gmail.com
License: UNKNOWN
Platform: UNKNOWN
